LICENSE
README.md
setup.py
Uni_Curses.egg-info/PKG-INFO
Uni_Curses.egg-info/SOURCES.txt
Uni_Curses.egg-info/dependency_links.txt
Uni_Curses.egg-info/not-zip-safe
Uni_Curses.egg-info/requires.txt
Uni_Curses.egg-info/top_level.txt
unicurses/__init__.py
unicurses/32 bit binaries/pdcdll/pdcurses.dll
unicurses/32 bit binaries/pdcdlls/LICENSE.freetype.txt
unicurses/32 bit binaries/pdcdlls/LICENSE.zlib.txt
unicurses/32 bit binaries/pdcdlls/SDL2.dll
unicurses/32 bit binaries/pdcdlls/SDL2_ttf.dll
unicurses/32 bit binaries/pdcdlls/libfreetype-6.dll
unicurses/32 bit binaries/pdcdlls/pdcurses.dll
unicurses/32 bit binaries/pdcdlls/zlib1.dll
unicurses/32 bit binaries/pdcdllu/pdcurses.dll
unicurses/32 bit binaries/pdcdllw/pdcurses.dll
unicurses/64 bit binaries/pdcdll/pdcurses.dll
unicurses/64 bit binaries/pdcdlls/LICENSE.freetype.txt
unicurses/64 bit binaries/pdcdlls/LICENSE.zlib.txt
unicurses/64 bit binaries/pdcdlls/SDL2.dll
unicurses/64 bit binaries/pdcdlls/SDL2_ttf.dll
unicurses/64 bit binaries/pdcdlls/libfreetype-6.dll
unicurses/64 bit binaries/pdcdlls/pdcurses.dll
unicurses/64 bit binaries/pdcdlls/zlib1.dll
unicurses/64 bit binaries/pdcdllu/pdcurses.dll
unicurses/64 bit binaries/pdcdllw/pdcurses.dll