Metadata-Version: 2.1
Name: Uni-Curses
Version: 2.1.7
Summary: Unified Curses Wrapper for Python
Home-page: https://github.com/unicurses/unicurses
Author: Michael Kamensky
Author-email: stavdev@mail.ru
Maintainer: George Chousos
Maintainer-email: gxousos@gmail.com
License: General Public License v3
Platform: Windows
Platform: FreeBSD
Platform: Linux
Platform: Mac OS X
License-File: LICENSE
